neoapi/__init__.py
neoapi/application_codes.py
neoapi/errors.py
neoapi/function_property.py
neoapi/http_error_codes.py
neoapi/neo_utils.py
neoapi/serializable_structured_node.py
neoapi/serializable_structured_node_base.py
neoapi-3.6.4.dist-info/DESCRIPTION.rst
neoapi-3.6.4.dist-info/METADATA
neoapi-3.6.4.dist-info/metadata.json
neoapi-3.6.4.dist-info/RECORD
neoapi-3.6.4.dist-info/top_level.txt
neoapi-3.6.4.dist-info/WHEEL
